setup.py
distributions/Binomialdistribution_challenge.py
distributions/Gaussiandistribution.py
distributions/Generaldistribution.py
distributions/__init__.py
distributions_vale15.egg-info/PKG-INFO
distributions_vale15.egg-info/SOURCES.txt
distributions_vale15.egg-info/dependency_links.txt
distributions_vale15.egg-info/not-zip-safe
distributions_vale15.egg-info/top_level.txt