Metadata-Version: 2.4
Name: distributions-vale15
Version: 0.1
Summary: Gaussian distributions
Dynamic: summary
